Metadata-Version: 1.0
Name: kokoridistributions
Version: 0.1
Summary: Gaussian and Binomial distributions
Home-page: UNKNOWN
Author: Ghislain Brice
Author-email: ghislainbrice@gmail.com
License: UNKNOWN
Platform: UNKNOWN
